skelate/__init__.py
skelate/cli.py
skelate/skeleton.py
skelate-0.0.2.dist-info/LICENSE
skelate-0.0.2.dist-info/METADATA
skelate-0.0.2.dist-info/WHEEL
skelate-0.0.2.dist-info/entry_points.txt
skelate-0.0.2.dist-info/top_level.txt
skelate-0.0.2.dist-info/RECORD
