Metadata-Version: 2.1
Name: skelate
Version: 0.0.2
Summary: Create directories from skeletons, with templating support.
Home-page: https://gitlab.com/iwaseatenbyagrue/skelate
Author: iwaseatenbyagrue
Author-email: iwaseatenbyagrue@gmail.com
License: BSD-3-Clause
Keywords: cli,skeleton,template
Platform: UNKNOWN
Classifier: License :: OSI Approved :: BSD License
Classifier: Programming Language :: Python :: 3
Classifier: Programming Language :: Python :: 3.8
Requires-Python: >=3.8
Requires-Dist: jinja2
Provides-Extra: test
Requires-Dist: tox ; extra == 'test'
Requires-Dist: pytest ; extra == 'test'
Requires-Dist: pytest-cov ; extra == 'test'
Requires-Dist: pytest-pep8 ; extra == 'test'
